{"cameraMode":{"drawMode":0,"name":"Shaded","section":"Shading Mode"},"sceneLighting":true,"audioPlay":false,"sceneViewState":{"m_AlwaysRefresh":false,"showFog":true,"showSkybox":true,"showFlares":true,"showImageEffects":true,"showParticleSystems":true,"showVisualEffectGraphs":true,"m_FxEnabled":true},"in2DMode":false,"pivot":{"x":-24.29954719543457,"y":25.286136627197267,"z":-46.851444244384769},"rotation":{"x":0.3466905951499939,"y":-0.036282192915678027,"z":0.013410180807113648,"w":0.937202513217926},"size":3.542358875274658,"orthographic":false}